model_picker/__init__.py
model_picker/model_picker.py
model_picker-0.0.4.dist-info/METADATA
model_picker-0.0.4.dist-info/RECORD
model_picker-0.0.4.dist-info/WHEEL
model_picker-0.0.4.dist-info/top_level.txt
