Metadata-Version: 2.1
Name: model-picker
Version: 0.0.4
Summary: Pick a model
Home-page: https://github.com/clement-alexandre/TotemBionet
Author: Alexandre Clement
Author-email: alexandre.clement@etu.unice.fr
License: WTFPL
Keywords: jupyter,computational systems biology
Platform: UNKNOWN
Classifier: Intended Audience :: Science/Research
Classifier: Topic :: Scientific/Engineering :: Bio-Informatics
Classifier: Programming Language :: Python :: 3.6
Classifier: Programming Language :: Python :: 3.7
